{
	"name": "Shain Initial QIF Trigger",
	"properties": {
		"annotations": [],
		"runtimeState": "Started",
		"pipelines": [
			{
				"pipelineReference": {
					"referenceName": "Initial_QIF_In_copy1",
					"type": "PipelineReference"
				},
				"parameters": {
					"FileName": "@triggerBody().fileName",
					"FilePath": "@triggerBody().folderPath"
				}
			}
		],
		"type": "BlobEventsTrigger",
		"typeProperties": {
			"blobPathBeginsWith": "/pythonin/blobs/",
			"blobPathEndsWith": ".qif",
			"ignoreEmptyBlobs": true,
			"scope": "/subscriptions/0fa38953-5cae-4448-b99b-2cb26dc3aa85/resourceGroups/AeroHubPlatform/providers/Microsoft.Storage/storageAccounts/aerohubblobstorage1",
			"events": [
				"Microsoft.Storage.BlobCreated"
			]
		}
	}
}